{
    "abilities": {
        "cute-charm": "Contact with the Pok\u00e9mon may cause infatuation.",
        "normalize": "All the Pok\u00e9mon\u2019s moves become Normal type.\nThe power of those moves is boosted a little.",
        "wonder-skin": "Makes status moves more likely to miss."
    },
    "description": {
        "game": "ruby",
        "text": "DELCATTY prefers to live an unfettered\nexistence in which it can do as it\npleases at its own pace.\fBecause this POK\u00e9MON eats and sleeps\nwhenever it decides, its daily routines\nare completely random."
    },
    "eggGroups": [
        "ground",
        "fairy"
    ],
    "evolution": {
        "end": [],
        "mid": [
            {
                "id": "301",
                "img": "https://raw.githubusercontent.com/BrianGHong/p-mock-api/main/api/img/301.png",
                "name": "delcatty",
                "types": [
                    "normal"
                ]
            }
        ],
        "start": [
            {
                "id": "300",
                "img": "https://raw.githubusercontent.com/BrianGHong/p-mock-api/main/api/img/300.png",
                "name": "skitty",
                "types": [
                    "normal"
                ]
            }
        ]
    },
    "forms": [
        {
            "back_default": "https://raw.githubusercontent.com/PokeAPI/sprites/master/sprites/pokemon/back/301.png"
        },
        {
            "back_shiny": "https://raw.githubusercontent.com/PokeAPI/sprites/master/sprites/pokemon/back/shiny/301.png"
        },
        {
            "front_default": "https://raw.githubusercontent.com/PokeAPI/sprites/master/sprites/pokemon/301.png"
        },
        {
            "front_shiny": "https://raw.githubusercontent.com/PokeAPI/sprites/master/sprites/pokemon/shiny/301.png"
        }
    ],
    "gender": {
        "female": 75.0,
        "male": 25.0
    },
    "genera": "Prim Pok\u00e9mon",
    "hatchCounter": 15,
    "height": 1.1,
    "id": 301,
    "img": "https://raw.githubusercontent.com/BrianGHong/p-mock-api/main/api/img/301.png",
    "name": "delcatty",
    "stats": {
        "attack": 65,
        "defense": 65,
        "hp": 70,
        "specialAttack": 55,
        "specialDefense": 55,
        "speed": 90
    },
    "type_relations": {
        "resistantTo": [],
        "weakTo": [
            "fighting"
        ]
    },
    "types": [
        "normal"
    ],
    "weight": 32.6
}