{
    "abilities": {
        "compound-eyes": "The Pok\u00e9mon\u2019s compound eyes boost its accuracy.",
        "run-away": "Enables a sure getaway from wild Pok\u00e9mon.",
        "tinted-lens": "The Pok\u00e9mon can use \u201cnot very effective\u201d moves\nto deal regular damage. "
    },
    "description": {
        "game": "red",
        "text": "Lives in the\nshadows of tall\ntrees where it\feats insects. It\nis attracted by\nlight at night."
    },
    "eggGroups": [
        "bug"
    ],
    "evolution": {
        "evolution_details": [],
        "evolves_to": [
            {
                "evolution_details": [
                    {
                        "gender": null,
                        "held_item": null,
                        "item": null,
                        "known_move": null,
                        "known_move_type": null,
                        "location": null,
                        "min_affection": null,
                        "min_beauty": null,
                        "min_happiness": null,
                        "min_level": 31,
                        "needs_overworld_rain": false,
                        "party_species": null,
                        "party_type": null,
                        "relative_physical_stats": null,
                        "time_of_day": "",
                        "trade_species": null,
                        "trigger": {
                            "name": "level-up",
                            "url": "https://pokeapi.co/api/v2/evolution-trigger/1/"
                        },
                        "turn_upside_down": false
                    }
                ],
                "evolves_to": [],
                "is_baby": false,
                "species": {
                    "name": "venomoth",
                    "url": "https://pokeapi.co/api/v2/pokemon-species/49/"
                }
            }
        ],
        "is_baby": false,
        "species": {
            "name": "venonat",
            "url": "https://pokeapi.co/api/v2/pokemon-species/48/"
        }
    },
    "forms": [
        {
            "back_default": "https://raw.githubusercontent.com/PokeAPI/sprites/master/sprites/pokemon/back/48.png"
        },
        {
            "back_shiny": "https://raw.githubusercontent.com/PokeAPI/sprites/master/sprites/pokemon/back/shiny/48.png"
        },
        {
            "front_default": "https://raw.githubusercontent.com/PokeAPI/sprites/master/sprites/pokemon/48.png"
        },
        {
            "front_shiny": "https://raw.githubusercontent.com/PokeAPI/sprites/master/sprites/pokemon/shiny/48.png"
        }
    ],
    "gender": {
        "female": 50.0,
        "male": 50.0
    },
    "genera": "Insect Pok\u00e9mon",
    "hatchCounter": 20,
    "height": 1.0,
    "id": 48,
    "img": "https://raw.githubusercontent.com/BrianGHong/p-mock-api/main/api/img/48.png",
    "name": "venonat",
    "stats": {
        "attack": 55,
        "defense": 50,
        "hp": 60,
        "specialAttack": 40,
        "specialDefense": 55,
        "speed": 45
    },
    "type_relations": {
        "resistantTo": [
            "fighting",
            "poison",
            "bug",
            "fairy",
            "grass"
        ],
        "weakTo": [
            "rock",
            "fire",
            "flying",
            "psychic"
        ]
    },
    "types": [
        "bug",
        "poison"
    ],
    "weight": 30.0
}