{
    "abilities": {
        "aftermath": "Damages the attacker if it contacts the Pok\u00e9mon\nwith a finishing hit.",
        "stench": "By releasing stench when attacking, this Pok\u00e9mon\nmay cause the target to flinch.",
        "weak-armor": "Physical attacks to the Pok\u00e9mon lower its Defense\nstat but sharply raise its Speed stat."
    },
    "description": {
        "game": "black",
        "text": "It clenches opponents with its left arm\nand finishes them off with foul-smelling\npoison gas belched from its mouth."
    },
    "eggGroups": [
        "mineral"
    ],
    "evolution": {
        "evolution_details": [],
        "evolves_to": [
            {
                "evolution_details": [
                    {
                        "gender": null,
                        "held_item": null,
                        "item": null,
                        "known_move": null,
                        "known_move_type": null,
                        "location": null,
                        "min_affection": null,
                        "min_beauty": null,
                        "min_happiness": null,
                        "min_level": 36,
                        "needs_overworld_rain": false,
                        "party_species": null,
                        "party_type": null,
                        "relative_physical_stats": null,
                        "time_of_day": "",
                        "trade_species": null,
                        "trigger": {
                            "name": "level-up",
                            "url": "https://pokeapi.co/api/v2/evolution-trigger/1/"
                        },
                        "turn_upside_down": false
                    }
                ],
                "evolves_to": [],
                "is_baby": false,
                "species": {
                    "name": "garbodor",
                    "url": "https://pokeapi.co/api/v2/pokemon-species/569/"
                }
            }
        ],
        "is_baby": false,
        "species": {
            "name": "trubbish",
            "url": "https://pokeapi.co/api/v2/pokemon-species/568/"
        }
    },
    "forms": [
        {
            "back_default": "https://raw.githubusercontent.com/PokeAPI/sprites/master/sprites/pokemon/back/569.png"
        },
        {
            "back_shiny": "https://raw.githubusercontent.com/PokeAPI/sprites/master/sprites/pokemon/back/shiny/569.png"
        },
        {
            "front_default": "https://raw.githubusercontent.com/PokeAPI/sprites/master/sprites/pokemon/569.png"
        },
        {
            "front_shiny": "https://raw.githubusercontent.com/PokeAPI/sprites/master/sprites/pokemon/shiny/569.png"
        }
    ],
    "gender": {
        "female": 50.0,
        "male": 50.0
    },
    "genera": "Trash Heap Pok\u00e9mon",
    "hatchCounter": 20,
    "height": 1.9,
    "id": 569,
    "img": "https://raw.githubusercontent.com/BrianGHong/p-mock-api/main/api/img/569.png",
    "name": "garbodor",
    "stats": {
        "attack": 95,
        "defense": 82,
        "hp": 80,
        "specialAttack": 60,
        "specialDefense": 82,
        "speed": 75
    },
    "type_relations": {
        "resistantTo": [
            "fighting",
            "poison",
            "bug",
            "fairy",
            "grass"
        ],
        "weakTo": [
            "psychic",
            "ground"
        ]
    },
    "types": [
        "poison"
    ],
    "weight": 107.3
}