{
    "abilities": {
        "big-pecks": "Protects the Pok\u00e9mon from\nDefense-lowering effects.",
        "overcoat": "Protects the Pok\u00e9mon from things like sand, hail,\nand powder.",
        "weak-armor": "Physical attacks to the Pok\u00e9mon lower its Defense\nstat but sharply raise its Speed stat."
    },
    "description": {
        "game": "black",
        "text": "Its wings are too tiny to allow it to fly.\nAs the time approaches for it to evolve,\nit discards the bones it was wearing."
    },
    "eggGroups": [
        "flying"
    ],
    "evolution": {
        "end": [],
        "mid": [
            {
                "id": "630",
                "img": "https://raw.githubusercontent.com/BrianGHong/p-mock-api/main/api/img/630.png",
                "name": "mandibuzz",
                "types": [
                    "dark",
                    "flying"
                ]
            }
        ],
        "start": [
            {
                "id": "629",
                "img": "https://raw.githubusercontent.com/BrianGHong/p-mock-api/main/api/img/629.png",
                "name": "vullaby",
                "types": [
                    "dark",
                    "flying"
                ]
            }
        ]
    },
    "forms": [
        {
            "back_default": "https://raw.githubusercontent.com/PokeAPI/sprites/master/sprites/pokemon/back/629.png"
        },
        {
            "back_shiny": "https://raw.githubusercontent.com/PokeAPI/sprites/master/sprites/pokemon/back/shiny/629.png"
        },
        {
            "front_default": "https://raw.githubusercontent.com/PokeAPI/sprites/master/sprites/pokemon/629.png"
        },
        {
            "front_shiny": "https://raw.githubusercontent.com/PokeAPI/sprites/master/sprites/pokemon/shiny/629.png"
        }
    ],
    "gender": {},
    "genera": "Diapered Pok\u00e9mon",
    "hatchCounter": 20,
    "height": 0.5,
    "id": 629,
    "img": "https://raw.githubusercontent.com/BrianGHong/p-mock-api/main/api/img/629.png",
    "name": "vullaby",
    "stats": {
        "attack": 55,
        "defense": 75,
        "hp": 70,
        "specialAttack": 45,
        "specialDefense": 65,
        "speed": 60
    },
    "type_relations": {
        "resistantTo": [
            "grass",
            "ghost",
            "dark"
        ],
        "weakTo": [
            "electric",
            "fairy",
            "rock",
            "ice"
        ]
    },
    "types": [
        "dark",
        "flying"
    ],
    "weight": 9.0
}