{
    "abilities": {
        "full-metal-body": "Prevents other Pok\u00e9mon\u2019s moves or Abilities from\nlowering the Pok\u00e9mon\u2019s stats."
    },
    "description": {
        "game": "sun",
        "text": "It is said to live in another world. The intense\nlight it radiates from the surface of its body can\nmake the darkest of nights light up like midday."
    },
    "eggGroups": [
        "no-eggs"
    ],
    "evolution": {
        "evolution_details": [],
        "evolves_to": [
            {
                "evolution_details": [
                    {
                        "gender": null,
                        "held_item": null,
                        "item": null,
                        "known_move": null,
                        "known_move_type": null,
                        "location": null,
                        "min_affection": null,
                        "min_beauty": null,
                        "min_happiness": null,
                        "min_level": 43,
                        "needs_overworld_rain": false,
                        "party_species": null,
                        "party_type": null,
                        "relative_physical_stats": null,
                        "time_of_day": "",
                        "trade_species": null,
                        "trigger": {
                            "name": "level-up",
                            "url": "https://pokeapi.co/api/v2/evolution-trigger/1/"
                        },
                        "turn_upside_down": false
                    }
                ],
                "evolves_to": [
                    {
                        "evolution_details": [
                            {
                                "gender": null,
                                "held_item": null,
                                "item": null,
                                "known_move": null,
                                "known_move_type": null,
                                "location": null,
                                "min_affection": null,
                                "min_beauty": null,
                                "min_happiness": null,
                                "min_level": 53,
                                "needs_overworld_rain": false,
                                "party_species": null,
                                "party_type": null,
                                "relative_physical_stats": null,
                                "time_of_day": "",
                                "trade_species": null,
                                "trigger": {
                                    "name": "level-up",
                                    "url": "https://pokeapi.co/api/v2/evolution-trigger/1/"
                                },
                                "turn_upside_down": false
                            }
                        ],
                        "evolves_to": [],
                        "is_baby": false,
                        "species": {
                            "name": "solgaleo",
                            "url": "https://pokeapi.co/api/v2/pokemon-species/791/"
                        }
                    },
                    {
                        "evolution_details": [
                            {
                                "gender": null,
                                "held_item": null,
                                "item": null,
                                "known_move": null,
                                "known_move_type": null,
                                "location": null,
                                "min_affection": null,
                                "min_beauty": null,
                                "min_happiness": null,
                                "min_level": 53,
                                "needs_overworld_rain": false,
                                "party_species": null,
                                "party_type": null,
                                "relative_physical_stats": null,
                                "time_of_day": "",
                                "trade_species": null,
                                "trigger": {
                                    "name": "level-up",
                                    "url": "https://pokeapi.co/api/v2/evolution-trigger/1/"
                                },
                                "turn_upside_down": false
                            }
                        ],
                        "evolves_to": [],
                        "is_baby": false,
                        "species": {
                            "name": "lunala",
                            "url": "https://pokeapi.co/api/v2/pokemon-species/792/"
                        }
                    }
                ],
                "is_baby": false,
                "species": {
                    "name": "cosmoem",
                    "url": "https://pokeapi.co/api/v2/pokemon-species/790/"
                }
            }
        ],
        "is_baby": false,
        "species": {
            "name": "cosmog",
            "url": "https://pokeapi.co/api/v2/pokemon-species/789/"
        }
    },
    "forms": [
        {
            "back_default": "https://raw.githubusercontent.com/PokeAPI/sprites/master/sprites/pokemon/back/791.png"
        },
        {
            "back_shiny": "https://raw.githubusercontent.com/PokeAPI/sprites/master/sprites/pokemon/back/shiny/791.png"
        },
        {
            "front_default": "https://raw.githubusercontent.com/PokeAPI/sprites/master/sprites/pokemon/791.png"
        },
        {
            "front_shiny": "https://raw.githubusercontent.com/PokeAPI/sprites/master/sprites/pokemon/shiny/791.png"
        }
    ],
    "gender": {
        "genderless": -12.5
    },
    "genera": "Sunne Pok\u00e9mon",
    "hatchCounter": 120,
    "height": 3.4,
    "id": 791,
    "img": "https://raw.githubusercontent.com/BrianGHong/p-mock-api/main/api/img/791.png",
    "name": "solgaleo",
    "stats": {
        "attack": 137,
        "defense": 107,
        "hp": 137,
        "specialAttack": 113,
        "specialDefense": 89,
        "speed": 97
    },
    "type_relations": {
        "resistantTo": [
            "rock",
            "fairy",
            "grass",
            "flying",
            "normal",
            "dragon",
            "psychic",
            "steel",
            "ice"
        ],
        "weakTo": [
            "dark",
            "fire",
            "ground",
            "ghost"
        ]
    },
    "types": [
        "psychic",
        "steel"
    ],
    "weight": 230.0
}