{
    "abilities": {
        "inner-focus": "The Pok\u00e9mon\u2019s intensely focused, and that protects\nthe Pok\u00e9mon from flinching."
    },
    "description": {
        "game": "sword",
        "text": "Kubfu trains hard to perfect its moves. The moves\nit masters will determine which form it takes when\nit evolves."
    },
    "eggGroups": [],
    "evolution": {
        "end": [],
        "mid": [
            {
                "id": "892",
                "img": "https://raw.githubusercontent.com/BrianGHong/p-mock-api/main/api/img/892.png",
                "name": "urshifu-single-strike",
                "types": [
                    "fighting",
                    "dark"
                ]
            }
        ],
        "start": [
            {
                "id": "891",
                "img": "https://raw.githubusercontent.com/BrianGHong/p-mock-api/main/api/img/891.png",
                "name": "kubfu",
                "types": [
                    "fighting"
                ]
            }
        ]
    },
    "forms": [
        {
            "back_default": "https://raw.githubusercontent.com/PokeAPI/sprites/master/sprites/pokemon/back/891.png"
        },
        {
            "back_shiny": "https://raw.githubusercontent.com/PokeAPI/sprites/master/sprites/pokemon/back/shiny/891.png"
        },
        {
            "front_default": "https://raw.githubusercontent.com/PokeAPI/sprites/master/sprites/pokemon/891.png"
        },
        {
            "front_shiny": "https://raw.githubusercontent.com/PokeAPI/sprites/master/sprites/pokemon/shiny/891.png"
        }
    ],
    "gender": {
        "female": 12.5,
        "male": 87.5
    },
    "genera": "Wushu Pok\u00e9mon",
    "hatchCounter": 120,
    "height": 0.6,
    "id": 891,
    "img": "https://raw.githubusercontent.com/BrianGHong/p-mock-api/main/api/img/891.png",
    "name": "kubfu",
    "stats": {
        "attack": 90,
        "defense": 60,
        "hp": 60,
        "specialAttack": 53,
        "specialDefense": 50,
        "speed": 72
    },
    "type_relations": {
        "resistantTo": [
            "dark",
            "rock",
            "bug"
        ],
        "weakTo": [
            "fairy",
            "psychic",
            "flying"
        ]
    },
    "types": [
        "fighting"
    ],
    "weight": 12.0
}